pyg_mongo/__init__.py
pyg_mongo/_base_reader.py
pyg_mongo/_cursor.py
pyg_mongo/_q.py
pyg_mongo/_reader.py
pyg_mongo/_table.py
pyg_mongo-0.0.15.dist-info/LICENSE
pyg_mongo-0.0.15.dist-info/METADATA
pyg_mongo-0.0.15.dist-info/WHEEL
pyg_mongo-0.0.15.dist-info/top_level.txt
pyg_mongo-0.0.15.dist-info/RECORD
