Metadata-Version: 2.1
Name: pyg-mongo
Version: 0.0.15
Summary: Utilities for data manipulation including creation of DAGs and tables
Home-page: https://github.com/gityoav/pyg-mongo
Author: Yoav Git
Author-email: yoav.git@gmail.com
Project-URL: Bug Tracker, https://github.com/gityoav/pyg-mongo/issues
Classifier: Programming Language :: Python :: 3
Classifier: License :: OSI Approved :: GNU General Public License v3 (GPLv3)
Classifier: Operating System :: OS Independent
Requires-Python: >=3.6
License-File: LICENSE
Requires-Dist: pyg-base
Requires-Dist: pymongo
Requires-Dist: dnspython
